{
  "id": "https://gamejolt.com/games/SLR/1043220",
  "name": "Boring Memory",
  "author": "Sister Location REDUX",
  "creators": ["mirk8lik3"],
  "verifier": "DarkMen",
  "verification": "https://youtu.be/seN1OS4bM4s?si=DOYKzsbAlhYxO3aY",
  "percentToQualify": "100",
  "password": "6 minutes",
  "date": "18/03/2026",
  "records": [
      { 
      "user": "Ytorad",
      "link": "https://www.youtube.com/watch?v=bUaojGNVOWg",
      "mins": 6,
      "secs": 0,
      "milisecs": "000",
      "date": "17/05/2026",
      "percent": "100"
      },
      { 
      "user": "Fallen_Moonlight_",
      "link": "https://youtu.be/wmt8D0y_4lg?si=vvjkkqtNMDNFshEL",
      "mins": 6,
      "secs": 0,
      "milisecs": "000",
      "date": "16/06/2026",
      "percent": "100"
      }
  ]
}
