{
	"id": "https://www.roblox.com/fr/games/92047183140382/Five-Nights-at-The-Gangs-Definitive-Edition",
	"name": "Nightmare at The Factory",
	"author": "Five Nights at The Gang's: Definitive Edition",
	"creators": ["WokenWoke"],
	"verifier": "letanguu",
	"verification": "https://www.youtube.com/watch?v=3YOIFY-Nz4Y",
	"percentToQualify": "100",
	"password": "6 minutes",
	"date": "27/02/2026",
	"records": [
            {
		        "user": "Hexzo",
		        "link": "https://youtu.be/Ev9rlH0lOWQ",
		        "mins": 6,
		        "secs": 0,
		        "milisecs": "000",
	        	"date": "29/03/2026",
		        "percent": "100"
		    }
    ]
}
